discord_py_utilities/__init__.py
discord_py_utilities/bans.py
discord_py_utilities/channels.py
discord_py_utilities/exceptions.py
discord_py_utilities/invites.py
discord_py_utilities/messages.py
discord_py_utilities/permissions.py
discord_py_utilities-0.0.9.7.dist-info/licenses/LICENSE.txt
discord_py_utilities-0.0.9.7.dist-info/METADATA
discord_py_utilities-0.0.9.7.dist-info/WHEEL
discord_py_utilities-0.0.9.7.dist-info/top_level.txt
discord_py_utilities-0.0.9.7.dist-info/RECORD
