Metadata-Version: 2.4
Name: discord-py-utilities
Version: 0.0.9.7
Summary: A collection of tools for Discord bots to enhance functionality and ease of use.
Home-page: https://github.com/wolfricoz/discord_tools
Author: Rico Stryker
Author-email: rico@strykerdevelopment.com
Project-URL: Bug Tracker, https://github.com/wolfricoz/discord_tools/issues
Classifier: Programming Language :: Python :: 3
Classifier: License :: OSI Approved :: MIT License
Classifier: Operating System :: OS Independent
Requires-Python: >=3.10
License-File: LICENSE.txt
Dynamic: license-file
